MANIFEST.in
README.rst
setup.py
peddler/__about__.py
peddler/__init__.py
peddler/bindmounts.py
peddler/config.py
peddler/env.py
peddler/exceptions.py
peddler/fmt.py
peddler/interactive.py
peddler/jobs.py
peddler/plugins.py
peddler/serialize.py
peddler/utils.py
peddler.egg-info/PKG-INFO
peddler.egg-info/SOURCES.txt
peddler.egg-info/dependency_links.txt
peddler.egg-info/entry_points.txt
peddler.egg-info/requires.txt
peddler.egg-info/top_level.txt
peddler/commands/__init__.py
peddler/commands/cli.py
peddler/commands/compose.py
peddler/commands/config.py
peddler/commands/context.py
peddler/commands/k8s.py
peddler/commands/local.py
peddler/templates/config.yml
peddler/templates/kustomization.yml
peddler/templates/version
peddler/templates/apps/caddy/Caddyfile
peddler/templates/apps/nginx/_peddler.conf
peddler/templates/apps/nginx/extra.conf
peddler/templates/apps/nginx/shop.conf
peddler/templates/cmd/opencart/init
peddler/templates/hooks/mysql/init
peddler/templates/k8s/deployments.yml
peddler/templates/k8s/jobs.yml
peddler/templates/k8s/namespace.yml
peddler/templates/k8s/services.yml
peddler/templates/k8s/volumes.yml
peddler/templates/local/docker-compose.jobs.yml
peddler/templates/local/docker-compose.yml
peddler/templates/themes/.DS_Store
peddler/templates/themes/Theme-Circlet-3x/changelog.txt
peddler/templates/themes/Theme-Circlet-3x/read-me.txt
peddler/templates/themes/Theme-Circlet-3x/upload/admin/controller/catalog/jade_testimonial.php
peddler/templates/themes/Theme-Circlet-3x/upload/admin/controller/extension/jade_customfooter.php
peddler/templates/themes/Theme-Circlet-3x/upload/admin/controller/extension/jade_customfooter_newsletter.php
peddler/templates/themes/Theme-Circlet-3x/upload/admin/controller/extension/jade_footer.php
peddler/templates/themes/Theme-Circlet-3x/upload/admin/controller/extension/jade_footer_copyright.php
peddler/templates/themes/Theme-Circlet-3x/upload/admin/controller/extension/jcirclet.php
peddler/templates/themes/Theme-Circlet-3x/upload/admin/controller/extension/module/j_category_list.php
peddler/templates/themes/Theme-Circlet-3x/upload/admin/controller/extension/module/jade_category.php
