Metadata-Version: 2.1
Name: peddler
Version: 0.0.3
Summary: The Docker-based OpenCart distribution for control-freaks
Home-page: UNKNOWN
Author: alto9.com
Author-email: contact@alto9.com
License: AGPLv3
Platform: UNKNOWN
